{
  "analysis-output.telemetry.mozilla.org": ["API", "Cloud Services"],
  "api.accounts.firefox.com": ["API", "Cloud Services"],
  "archive.mozilla.org": ["Windows XP Support"],
  "loop.services.mozilla.com": ["API", "Cloud Services"],
  "download-installer.cdn.mozilla.net": ["Windows XP Support"],
  "download.cdn.mozilla.net": ["Windows XP Support"],
  "download.mozilla.org": ["Windows XP Support"],
  "firefox.settings.services.mozilla.com": ["API", "Cloud Services"],
  "mozilla.org": ["Windows XP Support"],
  "oauth.accounts.firefox.com": ["API", "Cloud Services"],
  "profile.accounts.firefox.com": ["API", "Cloud Services"],
  "publicsuffix.org": ["Static Community Site"],
  "push.services.mozilla.com": ["API", "Cloud Services"],
  "search.services.mozilla.com": ["API", "Cloud Services"],
  "shavar.services.mozilla.com": ["API", "Cloud Services"],
  "status.services.mozilla.com": ["Cloud Services"],
  "sync-264-us-west-2.sync.services.mozilla.com": ["API", "Cloud Services"],
  "tiles.services.mozilla.com": ["API", "Cloud Services"],
  "tls-observatory.services.mozilla.com": ["API", "Cloud Services"],
  "token.services.mozilla.com": ["API", "Cloud Services"],
  "tracking.services.mozilla.com": ["API", "Cloud Services"],
  "updates.push.services.mozilla.com": ["API", "Cloud Services"],
  "verifier.accounts.firefox.com": ["API", "Cloud Services"],
  "webextensions.settings.services.mozilla.com": ["API", "Cloud Services"],

  "auth.taskcluster.net": ["API"],
  "aws-provisioner.taskcluster.net": ["API"],
  "cors-proxy.taskcluster.net": ["API"],
  "events.taskcluster.net": ["API"],
  "github.taskcluster.net": ["API"],
  "hooks.taskcluster.net": ["API"],
  "index.taskcluster.net": ["API"],
  "notify.taskcluster.net": ["API"],
  "public-artifacts.taskcluster.net": ["API"],
  "pulse.taskcluster.net": ["API"],
  "purge-cache.taskcluster.net": ["API"],
  "queue.taskcluster.net": ["API"],
  "scheduler.taskcluster.net": ["API"],
  "schemas.taskcluster.net": ["API"],
  "secrets.taskcluster.net": ["API"],

  "download-installer.cdn.mozilla.net": ["Duplicate"],
  "download.mozilla.org": ["Duplicate"],
  "ftp.mozilla.org": ["Duplicate"],
  "hello.firefox.com": ["Duplicate"],
  "releases.mozilla.com": ["Duplicate"],
  "releases.mozilla.org": ["Duplicate"],

  "mana.mozilla.org": ["SSO", "Manual Grade B"],
  "phonebook.mozilla.org": ["SSO", "Manual Grade A+"]
}
